bycon/__init__.py
bycon/config.py
bycon/byconServiceLibs/__init__.py
bycon/byconServiceLibs/bycon_bundler.py
bycon/byconServiceLibs/bycon_cluster.py
bycon/byconServiceLibs/bycon_importer.py
bycon/byconServiceLibs/bycon_plot.py
bycon/byconServiceLibs/collation_utils.py
bycon/byconServiceLibs/cytoband_utils.py
bycon/byconServiceLibs/datatable_utils.py
bycon/byconServiceLibs/export_file_generation.py
bycon/byconServiceLibs/file_utils.py
bycon/byconServiceLibs/geoloc_utils.py
bycon/byconServiceLibs/ontology_utils.py
bycon/byconServiceLibs/service_helpers.py
bycon/byconServiceLibs/service_response_generation.py
bycon/config/argument_definitions.yaml
bycon/config/beacon_configuration.yaml
bycon/config/beacon_map.yaml
bycon/config/dataset_definitions.yaml
bycon/config/datatable_mappings.yaml
bycon/config/filter_definitions.yaml
bycon/config/handover_definitions.yaml
bycon/config/interval_definitions.yaml
bycon/config/plot_defaults.yaml
bycon/config/services_configuration.yaml
bycon/config/services_map.yaml
bycon/config/variant_request_definitions.yaml
bycon/config/variant_type_definitions.yaml
bycon/lib/__init__.py
bycon/lib/beacon_auth.py
bycon/lib/beacon_responses.py
bycon/lib/bycon_helpers.py
bycon/lib/bycon_info.py
bycon/lib/bycon_summarizer.py
bycon/lib/genome_utils.py
bycon/lib/handover_generation.py
bycon/lib/interval_utils.py
bycon/lib/parameter_parsing.py
bycon/lib/query_execution.py
bycon/lib/query_generation.py
bycon/lib/response_remapping.py
bycon/lib/schema_parsing.py
bycon/lib/variant_mapping.py
bycon/lib/vrs_translator.py
bycon/rsrc/__init__.py
bycon/rsrc/genomes/grch38/cytoBandIdeo.txt
bycon/rsrc/genomes/grch38/refseq_chromosomes.yaml
bycon/rsrc/genomes/hg16/cytoBandIdeo.txt
bycon/rsrc/genomes/hg17/cytoBandIdeo.txt
bycon/rsrc/genomes/hg18/cytoBandIdeo.txt
bycon/rsrc/genomes/hg19/cytoBandIdeo.txt
bycon/rsrc/genomes/mSarHar1.11/cytoBandIdeo.txt
bycon/rsrc/genomes/mm8/cytoBandIdeo.txt
bycon/rsrc/genomes/mm9/cytoBandIdeo.txt
bycon-2.6.4.dist-info/licenses/LICENSE
bycon-2.6.4.dist-info/METADATA
bycon-2.6.4.dist-info/WHEEL
bycon-2.6.4.dist-info/top_level.txt
bycon-2.6.4.dist-info/RECORD
