Metadata-Version: 2.4
Name: bycon
Version: 2.6.4
Summary: A Python-based environment for the GA4GH Beacon genomics API
Author-email: Michael Baudis <m@baud.is>
License-Expression: CC0-1.0
Project-URL: source, https://github.com/progenetix/bycon
Project-URL: documentation, https://bycon.progenetix.org
Keywords: genomics,Beacon,GA4GH,Progenetix,MongoDB
Classifier: Intended Audience :: Developers
Classifier: Topic :: Internet :: WWW/HTTP :: Dynamic Content
Classifier: Topic :: Scientific/Engineering :: Bio-Informatics
Classifier: Topic :: Scientific/Engineering :: Interface Engine/Protocol Translator
Classifier: Topic :: Scientific/Engineering :: Medical Science Apps.
Classifier: Topic :: Software Development :: Libraries :: Python Modules
Requires-Python: >=3.8
License-File: LICENSE
Requires-Dist: base36
Requires-Dist: Cython
Requires-Dist: isodate
Requires-Dist: json_ref_dict
Requires-Dist: Markdown
Requires-Dist: numpy
Requires-Dist: Pillow
Requires-Dist: pyhumps
Requires-Dist: pymongo
Requires-Dist: PyYAML
Requires-Dist: scipy
Dynamic: license-file
